asyncio_portier/__init__.py
asyncio_portier/cache.py
asyncio_portier/client.py
asyncio_portier/py.typed
asyncio_portier/utils.py
asyncio_portier-0.3.0.dist-info/LICENSE
asyncio_portier-0.3.0.dist-info/METADATA
asyncio_portier-0.3.0.dist-info/WHEEL
asyncio_portier-0.3.0.dist-info/top_level.txt
asyncio_portier-0.3.0.dist-info/RECORD
