Metadata-Version: 2.1
Name: asyncio-portier
Version: 0.3.0
Summary: Portier authentication asyncio-aware Python helpers.
Home-page: https://github.com/vr2262/asyncio-portier
Author: Viktor Roytman
Author-email: viktor@viktorroytman.com
License: GPLv3
Keywords: web services
Platform: UNKNOWN
Classifier: Development Status :: 3 - Alpha
Classifier: Topic :: Internet :: WWW/HTTP
Classifier: Topic :: Internet :: WWW/HTTP :: WSGI :: Application
Classifier: License :: OSI Approved :: GNU General Public License v3 (GPLv3)
Classifier: Programming Language :: Python :: 3.9
Requires-Dist: cryptography
Requires-Dist: PyJWT
